aiohttp_session_mongo/__init__.py
aiohttp_session_mongo-0.0.1.dist-info/METADATA
aiohttp_session_mongo-0.0.1.dist-info/WHEEL
aiohttp_session_mongo-0.0.1.dist-info/top_level.txt
aiohttp_session_mongo-0.0.1.dist-info/RECORD
