Metadata-Version: 2.1
Name: aiohttp-session-mongo
Version: 0.0.1
Summary: mongo sessions for aiohttp.web
Home-page: https://github.com/alexpantyukhin/aiohttp-session-mongo/
Author: Alexander Pantyukhin
Author-email: apantykhin@gmail.com
License: Apache 2
Platform: UNKNOWN
Classifier: License :: OSI Approved :: Apache Software License
Classifier: Intended Audience :: Developers
Classifier: Programming Language :: Python
Classifier: Programming Language :: Python :: 3
Classifier: Programming Language :: Python :: 3.5
Classifier: Programming Language :: Python :: 3.6
Classifier: Topic :: Internet :: WWW/HTTP
Classifier: Framework :: AsyncIO
Requires-Python: >=3.5
Requires-Dist: aiohttp-session
Provides-Extra: motor
Requires-Dist: motor; extra == 'motor'
